collective.eeafaceted.z3ctable-2.30-py3.13-nspkg.pth
collective/eeafaceted/z3ctable/__init__.py
collective/eeafaceted/z3ctable/columns.py
collective/eeafaceted/z3ctable/columns.zcml
collective/eeafaceted/z3ctable/configure.zcml
collective/eeafaceted/z3ctable/interfaces.py
collective/eeafaceted/z3ctable/mk_sync_locales.sh
collective/eeafaceted/z3ctable/profiles.zcml
collective/eeafaceted/z3ctable/setuphandlers.py
collective/eeafaceted/z3ctable/testing.py
collective/eeafaceted/z3ctable/testing.zcml
collective/eeafaceted/z3ctable/browser/__init__.py
collective/eeafaceted/z3ctable/browser/configure.zcml
collective/eeafaceted/z3ctable/browser/default_collection.xml
collective/eeafaceted/z3ctable/browser/faceted-table-items.pt
collective/eeafaceted/z3ctable/browser/jsvariables.py
collective/eeafaceted/z3ctable/browser/overrides.py
collective/eeafaceted/z3ctable/browser/views.py
collective/eeafaceted/z3ctable/browser/widgets.py
collective/eeafaceted/z3ctable/browser/overrides/.gitkeep
collective/eeafaceted/z3ctable/browser/static/.gitkeep
collective/eeafaceted/z3ctable/browser/static/collective.eeafaceted.z3ctable.js
collective/eeafaceted/z3ctable/browser/static/refresh.gif
collective/eeafaceted/z3ctable/locales/collective.eeafaceted.z3ctable.pot
collective/eeafaceted/z3ctable/locales/manual.pot
collective/eeafaceted/z3ctable/locales/en/LC_MESSAGES/collective.eeafaceted.z3ctable.po
collective/eeafaceted/z3ctable/locales/fr/LC_MESSAGES/collective.eeafaceted.z3ctable.po
collective/eeafaceted/z3ctable/profiles/common/browserlayer.xml
collective/eeafaceted/z3ctable/profiles/common/collectiveeeafacetedz3ctable_marker.txt
collective/eeafaceted/z3ctable/profiles/common/metadata.xml
collective/eeafaceted/z3ctable/profiles/plone4/collectiveeeafacetedz3ctable_marker.txt
collective/eeafaceted/z3ctable/profiles/plone4/jsregistry.xml
collective/eeafaceted/z3ctable/profiles/plone4/metadata.xml
collective/eeafaceted/z3ctable/profiles/plone5/collectiveeeafacetedz3ctable_marker.txt
collective_eeafaceted_z3ctable-2.30.dist-info/licenses/LICENSE.rst
collective_eeafaceted_z3ctable-2.30.dist-info/METADATA
collective_eeafaceted_z3ctable-2.30.dist-info/WHEEL
collective_eeafaceted_z3ctable-2.30.dist-info/entry_points.txt
collective_eeafaceted_z3ctable-2.30.dist-info/namespace_packages.txt
collective_eeafaceted_z3ctable-2.30.dist-info/top_level.txt
collective_eeafaceted_z3ctable-2.30.dist-info/RECORD
