Metadata-Version: 2.4
Name: collective.eeafaceted.z3ctable
Version: 2.30
Summary: Package proposant un type de colonne compatible avec eea.facetednavigation
Home-page: http://pypi.python.org/pypi/collective.eeafaceted.z3ctable
Author: IMIO
Author-email: dev@imio.be
License: GPL V2
Keywords: Python Zope Plone
Classifier: Development Status :: 6 - Mature
Classifier: Environment :: Web Environment
Classifier: Framework :: Plone :: 4.3
Classifier: Framework :: Plone :: 5.0
Classifier: Framework :: Plone :: 5.1
Classifier: License :: OSI Approved :: GNU General Public License (GPL)
Classifier: Programming Language :: Python :: 2.7
License-File: LICENSE.rst
Requires-Dist: Plone
Requires-Dist: collective.excelexport<2.0
Requires-Dist: eea.facetednavigation<16.0
Requires-Dist: imio.helpers>=1.0.1
Requires-Dist: plone.api>=1.3.0
Requires-Dist: plone.formwidget.namedfile>=2.0.2
Requires-Dist: setuptools
Requires-Dist: z3c.table
Provides-Extra: test
Requires-Dist: imio.actionspanel; extra == "test"
Requires-Dist: imio.prettylink; extra == "test"
Requires-Dist: plone.app.dexterity; extra == "test"
Requires-Dist: plone.app.testing; extra == "test"
Requires-Dist: plone.app.relationfield; extra == "test"
Requires-Dist: plone.app.robotframework; extra == "test"
Provides-Extra: develop
Requires-Dist: zest.releaser; extra == "develop"
Dynamic: author
Dynamic: author-email
Dynamic: classifier
Dynamic: description
Dynamic: home-page
Dynamic: keywords
Dynamic: license
Dynamic: license-file
Dynamic: provides-extra
Dynamic: requires-dist
Dynamic: summary
